AUTHORS
LICENSE
MANIFEST.in
README.md
requirements.txt
setup.cfg
setup.py
test-requirements.txt
django_oauth10a_mod.egg-info/PKG-INFO
django_oauth10a_mod.egg-info/SOURCES.txt
django_oauth10a_mod.egg-info/dependency_links.txt
django_oauth10a_mod.egg-info/not-zip-safe
django_oauth10a_mod.egg-info/requires.txt
django_oauth10a_mod.egg-info/top_level.txt
oauth_provider/__init__.py
oauth_provider/admin.py
oauth_provider/authentication.py
oauth_provider/backends.py
oauth_provider/compat.py
oauth_provider/consts.py
oauth_provider/decorators.py
oauth_provider/forms.py
oauth_provider/managers.py
oauth_provider/models.py
oauth_provider/permissions.py
oauth_provider/responses.py
oauth_provider/urls.py
oauth_provider/utils.py
oauth_provider/views.py
oauth_provider/migrations/0001_initial.py
oauth_provider/migrations/__init__.py
oauth_provider/runtests/__init__.py
oauth_provider/runtests/manage.py
oauth_provider/runtests/runtests.py
oauth_provider/runtests/settings.py
oauth_provider/runtests/urls.py
oauth_provider/runtests/test_app/__init__.py
oauth_provider/runtests/test_app/models.py
oauth_provider/south_migrations/0001_initial.py
oauth_provider/south_migrations/0002_auto__add_field_consumer_xauth_allowed.py
oauth_provider/south_migrations/0003_auto__add_field_nonce_timestamp.py
oauth_provider/south_migrations/0004_resource_to_scope.py
oauth_provider/south_migrations/0005_auto__chg_field_token_scope.py
oauth_provider/south_migrations/__init__.py
oauth_provider/store/__init__.py
oauth_provider/store/db.py
oauth_provider/tests/__init__.py
oauth_provider/tests/auth.py
oauth_provider/tests/compat.py
oauth_provider/tests/decorators.py
oauth_provider/tests/issues.py
oauth_provider/tests/models.py
oauth_provider/tests/protocol.py
oauth_provider/tests/tests.py
oauth_provider/tests/xauth.py