Metadata-Version: 2.1
Name: django-oauth10a-mod
Version: 2.2.11
Summary: Support of OAuth 1.0a in Django using python-oauth10a.
Home-page: https://github.com/TimSC/django-oauth10a-mod
Author: Tim Sheerman-Chase
Author-email: dev@kinatomic.com
License: BSD
Platform: UNKNOWN
Classifier: Development Status :: 5 - Production/Stable
Classifier: Environment :: Web Environment
Classifier: Intended Audience :: Developers
Classifier: License :: OSI Approved :: BSD License
Classifier: Operating System :: OS Independent
Classifier: Programming Language :: Python
Classifier: Programming Language :: Python :: 2
Classifier: Programming Language :: Python :: 2.6
Classifier: Programming Language :: Python :: 2.7
Classifier: Programming Language :: Python :: 3
Classifier: Framework :: Django
Classifier: Framework :: Django :: 1.8
Classifier: Framework :: Django :: 1.10
Classifier: Framework :: Django :: 1.11
Classifier: Framework :: Django :: 2.0
License-File: LICENSE
License-File: AUTHORS
